svglob/__init__.py
svglob/__main__.py
svglob-0.0.1.dist-info/LICENSE
svglob-0.0.1.dist-info/METADATA
svglob-0.0.1.dist-info/WHEEL
svglob-0.0.1.dist-info/top_level.txt
svglob-0.0.1.dist-info/RECORD
