Metadata-Version: 2.1
Name: svglob
Version: 0.0.1
Summary: Combine SVG paths into one compound path.
Home-page: https://github.com/deckar01/svglob
Author: Jared Deckard
Author-email: jared@shademaps.com
License: UNKNOWN
Project-URL: Bug Tracker, https://github.com/deckar01/svglob/issues
Platform: UNKNOWN
Classifier: Programming Language :: Python :: 3
Classifier: License :: OSI Approved :: MIT License
Classifier: Operating System :: OS Independent
Requires-Python: >=3.6
License-File: LICENSE
Requires-Dist: numpy (==1.20.3)
Requires-Dist: svgwrite (==1.4.1)
Requires-Dist: svgpathtools (==1.4.1)
